ovhspams/__init__.py
ovhspams/domaines.py
ovhspams/tests.py
ovhspams/views.py
ovhspams/static/pyramid-16x16.png
ovhspams/static/pyramid.png
ovhspams/static/theme.css
ovhspams/templates/layout.pt
ovhspams/templates/mytemplate.pt
ovhspams-0.0.6.dist-info/DESCRIPTION.rst
ovhspams-0.0.6.dist-info/METADATA
ovhspams-0.0.6.dist-info/RECORD
ovhspams-0.0.6.dist-info/WHEEL
ovhspams-0.0.6.dist-info/entry_points.txt
ovhspams-0.0.6.dist-info/metadata.json
ovhspams-0.0.6.dist-info/top_level.txt
