Metadata-Version: 2.0
Name: ovhspams
Version: 0.0.6
Summary: Gestion des SAPMS avec les API OVH
Home-page: UNKNOWN
Author: Frédéric KIEBER
Author-email: contact@frkb.fr
License: GNU GPLv3
Keywords: web pyramid pylons spams ovh
Platform: UNKNOWN
Classifier: Development Status :: 3 - Alpha
Classifier: Programming Language :: Python
Classifier: Framework :: Pyramid
Classifier: Topic :: Internet :: WWW/HTTP
Classifier: Topic :: Internet :: WWW/HTTP :: WSGI :: Application
Requires-Dist: plaster-pastedeploy
Requires-Dist: pyramid
Requires-Dist: pyramid-chameleon
Requires-Dist: pyramid-debugtoolbar
Requires-Dist: waitress
Requires-Dist: deform
Requires-Dist: ovh
Provides-Extra: testing
Requires-Dist: WebTest (>=1.3.1); extra == 'testing'
Requires-Dist: pytest; extra == 'testing'
Requires-Dist: pytest-cov; extra == 'testing'
